babis/__init__.py
babis/babis.py
babis-0.2.4.dist-info/AUTHORS.rst
babis-0.2.4.dist-info/LICENSE
babis-0.2.4.dist-info/METADATA
babis-0.2.4.dist-info/WHEEL
babis-0.2.4.dist-info/top_level.txt
babis-0.2.4.dist-info/RECORD
