Metadata-Version: 2.1
Name: babis
Version: 0.2.4
Summary: Decorator that pings URLs before and after executing the wrapped obj.
Home-page: https://github.com/glogiotatidis/babis
Author: Giorgos Logiotatidis
Author-email: seadog@sealabs.net
License: GNU General Public License v3
Keywords: babis
Platform: UNKNOWN
Classifier: Development Status :: 4 - Beta
Classifier: Intended Audience :: Developers
Classifier: License :: OSI Approved :: GNU General Public License (GPL)
Classifier: Natural Language :: English
Classifier: Programming Language :: Python :: 2
Classifier: Programming Language :: Python :: 2.7
Classifier: Programming Language :: Python :: 3
Classifier: Programming Language :: Python :: 3.4
Classifier: Programming Language :: Python :: 3.5
Classifier: Programming Language :: Python :: 3.6
Requires-Dist: six (>=1.10)
